mr.developer-2.0.4-py3.13-nspkg.pth
mr/developer/bazaar.py
mr/developer/commands.py
mr/developer/common.py
mr/developer/compat.py
mr/developer/cvs.py
mr/developer/darcs.py
mr/developer/develop.py
mr/developer/extension.py
mr/developer/filesystem.py
mr/developer/git.py
mr/developer/gitsvn.py
mr/developer/mercurial.py
mr/developer/svn.py
mr/developer/tests/__init__.py
mr/developer/tests/conftest.py
mr/developer/tests/test_commands.py
mr/developer/tests/test_common.py
mr/developer/tests/test_cvs.py
mr/developer/tests/test_extension.py
mr/developer/tests/test_git.py
mr/developer/tests/test_git_submodules.py
mr/developer/tests/test_mercurial.py
mr/developer/tests/test_svn.py
mr/developer/tests/utils.py
mr.developer-2.0.4.dist-info/METADATA
mr.developer-2.0.4.dist-info/WHEEL
mr.developer-2.0.4.dist-info/entry_points.txt
mr.developer-2.0.4.dist-info/namespace_packages.txt
mr.developer-2.0.4.dist-info/top_level.txt
mr.developer-2.0.4.dist-info/RECORD
