Metadata-Version: 2.1
Name: mr.developer
Version: 2.0.4
Summary: A zc.buildout extension to ease the development of large projects with lots of packages.
Home-page: http://github.com/fschulze/mr.developer
Author: Florian Schulze
Author-email: florian.schulze@gmx.net
License: BSD
Keywords: buildout extension vcs git develop
Classifier: Development Status :: 5 - Production/Stable
Classifier: Programming Language :: Python
Classifier: Programming Language :: Python :: 2
Classifier: Programming Language :: Python :: 2.7
Classifier: Programming Language :: Python :: 3
Classifier: Programming Language :: Python :: 3.4
Classifier: Programming Language :: Python :: 3.5
Classifier: Programming Language :: Python :: 3.6
Classifier: Programming Language :: Python :: 3.7
Classifier: Programming Language :: Python :: 3.8
Classifier: Programming Language :: Python :: 3.9
Classifier: Programming Language :: Python :: 3.10
Classifier: Programming Language :: Python :: 3.11
Classifier: Programming Language :: Python :: 3.12
Classifier: Programming Language :: Python :: 3.13
Classifier: Framework :: Buildout
Classifier: Topic :: Software Development :: Libraries :: Python Modules
Requires-Python: >=2.7, !=3.0.*, !=3.1.*, !=3.2.*, !=3.3.*
Requires-Dist: setuptools
Requires-Dist: zc.buildout
Requires-Dist: six
Provides-Extra: test
Requires-Dist: mock; extra == "test"
